pdir/__init__.py
pdir/pdir.py
pdir_athesto-0.0.7.2.dist-info/LICENSE
pdir_athesto-0.0.7.2.dist-info/METADATA
pdir_athesto-0.0.7.2.dist-info/WHEEL
pdir_athesto-0.0.7.2.dist-info/top_level.txt
pdir_athesto-0.0.7.2.dist-info/RECORD
