Metadata-Version: 2.1
Name: pdir-athesto
Version: 0.0.7.2
Summary: pdir is a pretty print function for the dir() command.
Home-page: https://github.com/athesto/pretty-dir
Author: Gustavo Mejía
Author-email: gamez.live@gmail.com
License: UNKNOWN
Platform: UNKNOWN
Classifier: Programming Language :: Python :: 3
Classifier: License :: OSI Approved :: GNU General Public License v3 (GPLv3)
Classifier: Operating System :: OS Independent
Requires-Python: >=3.4
License-File: LICENSE
